Triangle_calculations_yes/Triangle.py
Triangle_calculations_yes/__init__.py
triangle_calculations_yes-0.0.5.dist-info/LICENSE
triangle_calculations_yes-0.0.5.dist-info/METADATA
triangle_calculations_yes-0.0.5.dist-info/WHEEL
triangle_calculations_yes-0.0.5.dist-info/top_level.txt
triangle_calculations_yes-0.0.5.dist-info/RECORD
