Metadata-Version: 2.1
Name: triangle_calculations_yes
Version: 0.0.5
Summary: Triangle calculations
Home-page: https://github.com/yesandnoandperhaps/Triangle
Author: LinQiuyun
Author-email: haizhimenhao@outlook.com
Classifier: Programming Language :: Python :: 3
Classifier: License :: OSI Approved :: MIT License
Classifier: Operating System :: OS Independent
Requires-Python: >=3.6
License-File: LICENSE
Requires-Dist: numpy
